{
  "appPageId" : "cb4d05bc-15d6-4e33-beb3-5244832ec585",
  "componentName" : "siteforce:sldsTwoCol84SidebarFeaturedLayout",
  "dataProviders" : [ ],
  "id" : "5abed2ca-5a1a-46e8-99e8-23f1406d0093",
  "label" : "Topic Detail",
  "regions" : [ {
    "components" : [ {
      "componentAttributes" : {
        "bannerText" : "",
        "bannerTextWithKnowledge" : "Explore other <a href=\"javascript:void(0)\" class=\"headlineArticles\">articles</a> and <a href=\"javascript:void(0)\" class=\"headlineDiscussions\">discussions</a> on this topic.",
        "bannerTextWithoutKnowledge" : "Explore other <a href=\"javascript:void(0)\" class=\"headlineDiscussions\">discussions</a> on this topic.",
        "pageType" : "topic",
        "showSubTopics" : true,
        "title" : "Welcome!",
        "uniqueNameOrId" : ""
      },
      "componentName" : "forceCommunity:headline",
      "id" : "a53bcf39-81d1-4213-a2b3-1dfaf7cd764e",
      "renderPriority" : "NEUTRAL",
      "renditionMap" : { },
      "type" : "component"
    } ],
    "id" : "beb199df-ef52-419d-ab6f-c776bca63190",
    "regionName" : "header",
    "type" : "region"
  }, {
    "components" : [ {
      "componentAttributes" : {
        "title" : "Description",
        "topicId" : "{!recordId}"
      },
      "componentName" : "forceCommunity:topicDescription",
      "id" : "fc2a9cc8-73ac-448c-8236-f091fe1a2ecc",
      "renderPriority" : "NEUTRAL",
      "renditionMap" : { },
      "type" : "component"
    }, {
      "componentAttributes" : {
        "showArticles" : true,
        "showFollowers" : true,
        "showPosts" : true,
        "showTalkingAbout" : true,
        "topicId" : "{!recordId}"
      },
      "componentName" : "forceCommunity:topicMetrics",
      "id" : "15c1e469-e96a-4832-8eb6-65b08531c1c9",
      "renderPriority" : "NEUTRAL",
      "renditionMap" : { },
      "type" : "component"
    }, {
      "componentAttributes" : {
        "buttonAlignment" : "center",
        "buttonBgColor" : "",
        "buttonBgHoverColor" : "",
        "buttonBorderColor" : "",
        "buttonMaxWidth" : 100,
        "buttonRadius" : 0,
        "buttonTextColor" : "",
        "buttonTextHoverColor" : "",
        "confirmationMessage" : "Got it!",
        "followUpPromptLabel" : "Can we close your question?",
        "isAskFollowPromptEnabled" : true,
        "isIncludeArticlesEnabled" : false,
        "isIncludeDiscussionsEnabled" : true,
        "isInitialSatisfactionPromptEnabled" : true,
        "isPublisherDeflectionEnabled" : true,
        "label" : "Ask a Question",
        "maxSuggestions" : 5,
        "satisfactionPromptLabel" : "Did we help to answer your question?",
        "showDetails" : false,
        "showTopics" : true,
        "uneditableTopics" : false
      },
      "componentName" : "forceCommunity:askCommunity",
      "id" : "32605755-e970-4328-86e6-11ec4101768b",
      "renderPriority" : "NEUTRAL",
      "renditionMap" : { },
      "type" : "component"
    }, {
      "componentAttributes" : {
        "buttonAlignment" : "center",
        "buttonBgColor" : "",
        "buttonBgHoverColor" : "",
        "buttonBorderColor" : "",
        "buttonMaxWidth" : 100,
        "buttonRadius" : 0,
        "buttonTextColor" : "",
        "buttonTextHoverColor" : "",
        "recordId" : "{!recordId}",
        "showNotificationMenu" : true
      },
      "componentName" : "forceCommunity:follow",
      "id" : "ece4dc36-19c1-42de-8307-73a79b793333",
      "renderPriority" : "NEUTRAL",
      "renditionMap" : { },
      "type" : "component"
    } ],
    "id" : "91dc22cc-6604-49d0-aae9-7f52efe4b816",
    "regionName" : "featured",
    "type" : "region"
  }, {
    "components" : [ {
      "componentAttributes" : {
        "activeTab" : "{!selectedTab}",
        "articleListPageSize" : 10,
        "articleTabLabel" : "Articles",
        "defaultSortOrderCompactFeed" : "Relevance",
        "defaultSortOrderFullFeed" : "Relevance",
        "discussionTabLabel" : "Discussions",
        "searchTerm" : "{!term}",
        "showArticleTab" : true,
        "showCompactFeedInDiscussion" : true,
        "topicId" : "{!recordId}"
      },
      "componentName" : "forceCommunity:resultsList",
      "id" : "44caafd8-2fd3-4252-82b9-084327e94147",
      "renderPriority" : "NEUTRAL",
      "renditionMap" : { },
      "type" : "component"
    } ],
    "id" : "3ba385e5-e098-44a1-b7be-1b3f29508fb5",
    "regionName" : "content",
    "type" : "region"
  }, {
    "components" : [ {
      "componentAttributes" : {
        "showTopicsMetric" : true,
        "title" : "Related Topics",
        "topicId" : "{!recordId}"
      },
      "componentName" : "forceCommunity:relatedTopics",
      "id" : "ce33356f-0b3a-40ec-842b-ef6e7d39d259",
      "renderPriority" : "NEUTRAL",
      "renditionMap" : { },
      "type" : "component"
    }, {
      "componentAttributes" : {
        "title" : "Knowledgeable People",
        "topicId" : "{!recordId}"
      },
      "componentName" : "forceCommunity:knowledgeablePeople",
      "id" : "68ac07b5-cedf-494a-a1c4-c11420e6dbc9",
      "renderPriority" : "NEUTRAL",
      "renditionMap" : { },
      "type" : "component"
    } ],
    "id" : "84571c60-7f01-4132-8c98-9c2ead192c06",
    "regionName" : "sidebar",
    "type" : "region"
  }, {
    "components" : [ {
      "componentAttributes" : {
        "askCommunityLabel" : "Ask a Question",
        "buttonBgColor" : "",
        "buttonBgHoverColor" : "",
        "buttonBorderColor" : "",
        "buttonRadius" : 0,
        "buttonTextColor" : "",
        "buttonTextHoverColor" : "",
        "buttonTwoBgColor" : "",
        "buttonTwoBgHoverColor" : "",
        "buttonTwoBorderColor" : "",
        "buttonTwoRadius" : 0,
        "buttonTwoTextColor" : "",
        "buttonTwoTextHoverColor" : "",
        "confirmationMessage" : "Got it!",
        "contactSupportLabel" : "Contact Support",
        "followUpPromptLabel" : "Can we close your question?",
        "headerLabel" : "Don't see what you're looking for?",
        "isAskFollowPromptEnabled" : true,
        "isIncludeArticlesEnabled" : false,
        "isIncludeDiscussionsEnabled" : true,
        "isInitialSatisfactionPromptEnabled" : true,
        "isPublisherDeflectionEnabled" : true,
        "maxSuggestions" : 5,
        "satisfactionPromptLabel" : "Did we help to answer your question?",
        "showDetails" : false,
        "showTopics" : true
      },
      "componentName" : "siteforce:napiliFooter",
      "id" : "b4a6e022-60a8-44bc-8378-7f156ccf46e6",
      "renderPriority" : "NEUTRAL",
      "renditionMap" : { },
      "type" : "component"
    } ],
    "id" : "cfee6844-b021-4e48-ac58-bf7d027e9999",
    "regionName" : "footer",
    "type" : "region"
  }, {
    "components" : [ {
      "componentAttributes" : {
        "customHeadTags" : "",
        "description" : "{!Record.Description}",
        "title" : "{!Record._Title}"
      },
      "componentName" : "forceCommunity:seoAssistant",
      "id" : "8f9f6d25-dd41-4f62-a6b1-ce0d743ba0e8",
      "renditionMap" : { },
      "type" : "component"
    } ],
    "id" : "00038ac8-e83c-4911-b51f-488cc9781536",
    "regionName" : "sfdcHiddenRegion",
    "type" : "region"
  } ],
  "themeLayoutType" : "Inner",
  "type" : "view",
  "viewType" : "topic"
}